recentearthquake/__init__.py
recentearthquake-0.3.dist-info/LICENSE
recentearthquake-0.3.dist-info/METADATA
recentearthquake-0.3.dist-info/WHEEL
recentearthquake-0.3.dist-info/top_level.txt
recentearthquake-0.3.dist-info/RECORD
