Metadata-Version: 2.1
Name: recentearthquake
Version: 0.3
Summary: This package will get recent earthquake from BMKG (Meteorological, Climatological, and Geophysical Agency)
Home-page: https://github.com/arifs16/recent-indonesia-earthquake
Author: Arif Setyadi
Author-email: arifsetyadi16@gmail.com
Project-URL: My account, https://github.com/arifs16
Classifier: Programming Language :: Python :: 3
Classifier: License :: OSI Approved :: GNU General Public License v3 (GPLv3)
Classifier: Operating System :: OS Independent
Classifier: Development Status :: 5 - Production/Stable
Requires-Python: >=3.6
License-File: LICENSE
